koksszachy/__init__.py
koksszachy/engine.py
koksszachy/play.py
koksszachy/selfplay.py
koksszachy/static/favicon.png
koksszachy/static/index.js
koksszachy/static/logo.png
koksszachy/static/style.css
koksszachy/static/style.scss
koksszachy/static/img/chesspieces/custom/bB.png
koksszachy/static/img/chesspieces/custom/bK.png
koksszachy/static/img/chesspieces/custom/bN.png
koksszachy/static/img/chesspieces/custom/bP.png
koksszachy/static/img/chesspieces/custom/bQ.png
koksszachy/static/img/chesspieces/custom/bR.png
koksszachy/static/img/chesspieces/wikipedia/bB.png
koksszachy/static/img/chesspieces/wikipedia/bK.png
koksszachy/static/img/chesspieces/wikipedia/bN.png
koksszachy/static/img/chesspieces/wikipedia/bP.png
koksszachy/static/img/chesspieces/wikipedia/bQ.png
koksszachy/static/img/chesspieces/wikipedia/bR.png
koksszachy/static/img/chesspieces/wikipedia/wB.png
koksszachy/static/img/chesspieces/wikipedia/wK.png
koksszachy/static/img/chesspieces/wikipedia/wN.png
koksszachy/static/img/chesspieces/wikipedia/wP.png
koksszachy/static/img/chesspieces/wikipedia/wQ.png
koksszachy/static/img/chesspieces/wikipedia/wR.png
koksszachy/static/lib/chess.js
koksszachy/static/lib/chessboard.min.css
koksszachy/static/lib/chessboard.min.js
koksszachy/static/lib/jquery.min.js
koksszachy/templates/.selfplay_index.html.swp
koksszachy/templates/index.html
koksszachy/templates/selfplay.html
KoksSzachy-0.8.52.dist-info/LICENSE
KoksSzachy-0.8.52.dist-info/METADATA
KoksSzachy-0.8.52.dist-info/WHEEL
KoksSzachy-0.8.52.dist-info/entry_points.txt
KoksSzachy-0.8.52.dist-info/top_level.txt
KoksSzachy-0.8.52.dist-info/RECORD
