Metadata-Version: 2.1
Name: KoksSzachy
Version: 0.8.52
Summary: Lubisz grać w szachy? Podobał ci się chess.com lub lichess? W takim razie pokochasz KoksSzachy! <3
Home-page: https://github.com/a1eaiactaest/KoksSzachy
Author: a1eaiactaest,czajaproggramer,AeroRocket,igoy1,Kajtek-creator
License: MIT
Platform: UNKNOWN
Requires-Python: >=3.7
Requires-Dist: Flask
Requires-Dist: chess
Requires-Dist: flask-ngrok
Requires-Dist: numpy
Requires-Dist: pytest
Requires-Dist: requests
